autodistill_codet/__init__.py
autodistill_codet/codet_model.py
autodistill_codet/predictor.py
autodistill_codet-0.1.2.dist-info/LICENSE
autodistill_codet-0.1.2.dist-info/METADATA
autodistill_codet-0.1.2.dist-info/WHEEL
autodistill_codet-0.1.2.dist-info/top_level.txt
autodistill_codet-0.1.2.dist-info/RECORD
